[
  {
    "section": "A. 원문 피드백",
    "item": "클라이언트 원문",
    "example": "\"좀 더 고급스럽게 해주세요. 근데 너무 올드하진 않게요.\"",
    "guide": "클라이언트가 말한 그대로 기록. 편집 금지."
  },
  {
    "section": "A. 원문 피드백",
    "item": "피드백 유형",
    "example": "방향형 + 부정형 복합",
    "guide": "트리거 사전 시트 1 참조"
  },
  {
    "section": "A. 원문 피드백",
    "item": "맥락 정보",
    "example": "뷰티 / 프리미엄 / 1차 시안 피드백 / 30대 타깃",
    "guide": "시트 4 맥락변수 참조"
  },
  {
    "section": "B. 해석 요약\n(클라이언트 확인용)",
    "item": "클라이언트에게 보여줄 요약",
    "example": "\"말씀하신 '고급스러움'은 전통적이고 무거운 느낌보다는, 비워내서 여유 있는 고급감에 가까운 것 같아요. 맞으신가요?\"",
    "guide": "비전문가 언어로. 클라이언트가 '맞아요/아니에요' 판단 가능하게."
  },
  {
    "section": "C. 전략 해석",
    "item": "포지셔닝 맥락",
    "example": "대중 통신 브랜드의 영타깃 캠페인에서 '프리미엄'은 가격이 아니라 감성 품질. 경쟁사 대비 '친근하지만 세련된' 틈새.",
    "guide": "왜 이 방향이 브랜드 전략에 부합하는지. AE가 클라이언트에게 설명할 근거."
  },
  {
    "section": "C. 전략 해석",
    "item": "클라이언트 설득 포인트",
    "example": "'싸 보일까 걱정'에 대해 → '친근함 ≠ 저가. NAT-B는 자연스러운 소재감과 여백으로 품질을 표현합니다'",
    "guide": "클라이언트가 가질 수 있는 우려에 대한 대응 논리."
  },
  {
    "section": "D. 해석 요약\n(디자이너용)",
    "item": "확정 분기",
    "example": "LUX-B (미니멀 럭셔리) — 주방향\nSOP-B (코리안 세련) — 보조 참조",
    "guide": "주방향 1개 + 보조 참조 0~1개. 3개 이상이면 수렴 실패."
  },
  {
    "section": "D. 해석 요약\n(디자이너용)",
    "item": "배제 분기",
    "example": "LUX-A (올드머니 클래식) — 클라이언트가 '올드하지 않게'로 명시 배제\nLUX-D (맥시멀 글램) — 맥락상 부적합",
    "guide": "클라이언트가 직접 배제한 것과 맥락상 배제를 구분."
  },
  {
    "section": "D. 해석 요약\n(디자이너용)",
    "item": "해석 근거 요약",
    "example": "Q1 '묵직한 느낌 vs 비운 느낌' → 비운 느낌 선택\nQ2 '전통적 격조 vs 현대적 절제' → 현대적 절제 선택\n'올드하지 않게'라는 명시 부정 → LUX-A 배제",
    "guide": "질문-응답 로그 핵심만 요약. 의사결정 추적 가능하게."
  },
  {
    "section": "E. 핵심 조정 포인트",
    "item": "컬러",
    "example": "현재 시안의 골드 톤 → 뮤트 베이지/그레이로 전환. 팔레트 3색 이내로 축소. 채도 전체적으로 30% 낮추기",
    "guide": "시트 3 디자인토큰 해당 분기 참조. '현재 대비' 방향으로 기술."
  },
  {
    "section": "E. 핵심 조정 포인트",
    "item": "서체",
    "example": "현재 장식적 세리프 → 네오그로테스크 산세리프로 전환. 웨이트 Light~Regular. 자간 넓히기",
    "guide": ""
  },
  {
    "section": "E. 핵심 조정 포인트",
    "item": "레이아웃",
    "example": "여백 비율 현재 대비 1.5배 확대. 요소 수 40% 줄이기. 대칭 → 비대칭 전환 고려",
    "guide": ""
  },
  {
    "section": "E. 핵심 조정 포인트",
    "item": "이미지/사진",
    "example": "하이키 라이팅으로 전환. 배경 단순화. 오브제 수 줄이기",
    "guide": ""
  },
  {
    "section": "E. 핵심 조정 포인트",
    "item": "질감/텍스처",
    "example": "현재 글로시 마감 → 매트/무광으로. 콘크리트, 면 질감 참고",
    "guide": ""
  },
  {
    "section": "F. 절대 하지 말 것",
    "item": "배제 토큰",
    "example": "높은 정보밀도 금지. 그래디언트 금지. 장식적 서체 유지 금지. 모노스페이스 금지. 다크모드 전환 금지",
    "guide": "시트 3 '절대 하지 말 것' + 시트 2 '배제 토큰' 종합"
  },
  {
    "section": "F. 절대 하지 말 것",
    "item": "흔한 실수 경고",
    "example": "⚠️ LUX-B를 CLN-A(스위스 미니멀)로 해석하는 실수 주의. LUX-B는 '여유의 비움'이지 '기능의 정돈'이 아님. 여백의 의도가 다름.",
    "guide": "시트 2 혼동 분기 + 핵심 구분 축 참조. 가장 중요한 경고."
  },
  {
    "section": "G. 레퍼런스 방향",
    "item": "참조 브랜드",
    "example": "Celine 2023-2024 캠페인 / Bottega Veneta 매장 비주얼 / Aesop 패키지",
    "guide": "특정 캠페인/시즌까지 명시하면 더 정확."
  },
  {
    "section": "G. 레퍼런스 방향",
    "item": "안티 레퍼런스",
    "example": "Louis Vuitton 모노그램 (장식 과잉) / Tiffany (클래식 과잉) / Apple Store (테크 과잉)",
    "guide": "'이 방향은 아닙니다'를 보여주는 구체적 예시."
  }
]